shiftlab_ocr/__init__.py
shiftlab_ocr/doc2text/__init__.py
shiftlab_ocr/doc2text/crop.py
shiftlab_ocr/doc2text/paths.py
shiftlab_ocr/doc2text/reader.py
shiftlab_ocr/doc2text/recognition.py
shiftlab_ocr/doc2text/segmentation.py
shiftlab_ocr/doc2text/weights/__init__.py
shiftlab_ocr/doc2text/yolov5/__init__.py
shiftlab_ocr/doc2text/yolov5/detect.py
shiftlab_ocr/doc2text/yolov5/export.py
shiftlab_ocr/doc2text/yolov5/hubconf.py
shiftlab_ocr/doc2text/yolov5/models/__init__.py
shiftlab_ocr/doc2text/yolov5/models/common.py
shiftlab_ocr/doc2text/yolov5/models/experimental.py
shiftlab_ocr/doc2text/yolov5/models/tf.py
shiftlab_ocr/doc2text/yolov5/models/yolo.py
shiftlab_ocr/doc2text/yolov5/utils/__init__.py
shiftlab_ocr/doc2text/yolov5/utils/activations.py
shiftlab_ocr/doc2text/yolov5/utils/augmentations.py
shiftlab_ocr/doc2text/yolov5/utils/autoanchor.py
shiftlab_ocr/doc2text/yolov5/utils/autobatch.py
shiftlab_ocr/doc2text/yolov5/utils/benchmarks.py
shiftlab_ocr/doc2text/yolov5/utils/callbacks.py
shiftlab_ocr/doc2text/yolov5/utils/dataloaders.py
shiftlab_ocr/doc2text/yolov5/utils/downloads.py
shiftlab_ocr/doc2text/yolov5/utils/general.py
shiftlab_ocr/doc2text/yolov5/utils/loss.py
shiftlab_ocr/doc2text/yolov5/utils/metrics.py
shiftlab_ocr/doc2text/yolov5/utils/plots.py
shiftlab_ocr/doc2text/yolov5/utils/torch_utils.py
shiftlab_ocr/generator/__init__.py
shiftlab_ocr/generator/font.py
shiftlab_ocr/generator/generator.py
shiftlab_ocr/generator/content/Jayadhira.ttf
shiftlab_ocr/generator/content/__init__.py
shiftlab_ocr/generator/content/amandasignature.ttf
shiftlab_ocr/generator/content/back.png
shiftlab_ocr/generator/content/back1.png
shiftlab_ocr/generator/content/back_wide.png
shiftlab_ocr/generator/content/bimbo.regular.ttf
shiftlab_ocr/generator/content/dark2.png
shiftlab_ocr/generator/content/dark2_wide.png
shiftlab_ocr/generator/content/dark_wide.png
shiftlab_ocr/generator/content/form1.png
shiftlab_ocr/generator/content/form2.png
shiftlab_ocr_test-0.3.2.dist-info/METADATA
shiftlab_ocr_test-0.3.2.dist-info/WHEEL
shiftlab_ocr_test-0.3.2.dist-info/top_level.txt
shiftlab_ocr_test-0.3.2.dist-info/RECORD
